esl_babylon_callm/__init__.py
esl_babylon_callm/callm.py
esl_babylon_callm/config.py
esl_babylon_callm/env.ini
esl_babylon_callm/utils/__init__.py
esl_babylon_callm/utils/get_memory.py
esl_babylon_callm/utils/get_prompt_template.py
esl_babylon_callm/utils/logger/__init__.py
esl_babylon_callm/utils/logger/create_logger.py
esl_babylon_callm/utils/logger/formatter.py
esl_babylon_callm-0.2.0.dist-info/LICENSE
esl_babylon_callm-0.2.0.dist-info/METADATA
esl_babylon_callm-0.2.0.dist-info/WHEEL
esl_babylon_callm-0.2.0.dist-info/RECORD
