Metadata-Version: 2.1
Name: esl-babylon-callm
Version: 0.2.0
Summary: 
Author: epam
Requires-Python: >=3.11,<4.0
Classifier: Programming Language :: Python :: 3
Classifier: Programming Language :: Python :: 3.11
Classifier: Programming Language :: Python :: 3.12
Requires-Dist: langchain (>=0.0.335,<0.0.336)
Requires-Dist: pydantic (>=2.4.2,<3.0.0)
Requires-Dist: pydantic-settings (>=2.0.3,<3.0.0)
Requires-Dist: redis (>=5.0.1,<6.0.0)
Requires-Dist: sqlalchemy (>=2.0.23,<3.0.0)
